latexlate/CodeBuilder.py
latexlate/StandartFilters.py
latexlate/SuperRenderer.py
latexlate/Template.py
latexlate/TokenAnalyzer.py
latexlate/__init__.py
latexlate/Errors/SyntaxError.py
latexlate/Errors/__init__.py
latexlate/tests/__init__.py
latexlate/tests/test_TokenAnalyzer.py
latexlate-1.1.6.dist-info/METADATA
latexlate-1.1.6.dist-info/RECORD
latexlate-1.1.6.dist-info/WHEEL
latexlate-1.1.6.dist-info/top_level.txt
