Metadata-Version: 2.1
Name: latexlate
Version: 1.1.6
Summary: A small template language for LaTeX, now with support for wolfram mathematica
Home-page: https://gitlab.com/nanopro/latexlate
Author: Nanopro
Author-email: nanopro1g@gmail.com
License: UNKNOWN
Platform: UNKNOWN
Classifier: Programming Language :: Python :: 3
Classifier: License :: OSI Approved :: MIT License
Classifier: Operating System :: OS Independent
Requires-Python: >=3.6
